ret/__init__.py
ret/cli.py
ret/plot.py
ret/templates/plot_script.py
rettool-0.0.1.dist-info/METADATA
rettool-0.0.1.dist-info/WHEEL
rettool-0.0.1.dist-info/entry_points.txt
rettool-0.0.1.dist-info/top_level.txt
rettool-0.0.1.dist-info/RECORD
