Metadata-Version: 2.1
Name: rettool
Version: 0.0.1
Summary: Tool to help in running experiments and saving logs
Home-page: https://github.com/nifey/ret
License: MIT
Project-URL: Bug Tracker, https://github.com/nifey/ret/issues
Classifier: Programming Language :: Python :: 3
Classifier: License :: OSI Approved :: MIT License
Classifier: Operating System :: OS Independent
Classifier: Environment :: Console
Classifier: Development Status :: 3 - Alpha
Requires-Dist: click (>=8.1.3)
Requires-Dist: Jinja2 (>=3.1.2)
Requires-Dist: matplotlib (>=3.5.3)
Requires-Dist: numpy (>=1.23.2)
Requires-Dist: PyYAML (>=6.0)
